{
  "db_name": "PostgreSQL",
  "query": "INSERT INTO users\n        (username, email, password, has_stylesheet, pfp_ext, banner_ext, biography, admin)\n        VALUES ($1, $2, $3, false, NULL, NULL, '', false)\n        RETURNING id, username, has_stylesheet, pfp_ext, banner_ext, biography, admin",
  "describe": {
    "columns": [
      {
        "ordinal": 0,
        "name": "id",
        "type_info": "Int8"
      },
      {
        "ordinal": 1,
        "name": "username",
        "type_info": "Varchar"
      },
      {
        "ordinal": 2,
        "name": "has_stylesheet",
        "type_info": "Bool"
      },
      {
        "ordinal": 3,
        "name": "pfp_ext",
        "type_info": "Varchar"
      },
      {
        "ordinal": 4,
        "name": "banner_ext",
        "type_info": "Varchar"
      },
      {
        "ordinal": 5,
        "name": "biography",
        "type_info": "Varchar"
      },
      {
        "ordinal": 6,
        "name": "admin",
        "type_info": "Bool"
      }
    ],
    "parameters": {
      "Left": [
        "Varchar",
        "Varchar",
        "Varchar"
      ]
    },
    "nullable": [
      false,
      false,
      false,
      true,
      true,
      false,
      false
    ]
  },
  "hash": "2deef9c6f33fb19efb45b34682b8a3cdb01f3521853420d3d0a3ac24c891ec81"
}
